awsiotclient/__init__.py
awsiotclient/classic_shadow.py
awsiotclient/dictdiff.py
awsiotclient/jobs.py
awsiotclient/mqtt.py
awsiotclient/named_shadow.py
awsiotclient/pubsub.py
awsiotclient/shadow.py
awsiotclient-0.2.1.dist-info/LICENSE
awsiotclient-0.2.1.dist-info/METADATA
awsiotclient-0.2.1.dist-info/WHEEL
awsiotclient-0.2.1.dist-info/RECORD
