Metadata-Version: 2.1
Name: awsiotclient
Version: 0.2.1
Summary: The AWS IoT Device Client provides device-side functionality for AWS IoT services such as jobs, device shadow, and simple pubsub.
Home-page: https://github.com/whill-labs/aws-iot-device-client-python
License: Apache-2.0
Author: Seiya Shimizu
Author-email: seiya.shimizu@gmail.com
Requires-Python: >=3.7.1,<4.0.0
Classifier: License :: OSI Approved :: Apache Software License
Classifier: Programming Language :: Python :: 3
Classifier: Programming Language :: Python :: 3.8
Classifier: Programming Language :: Python :: 3.9
Classifier: Programming Language :: Python :: 3.10
Classifier: Programming Language :: Python :: 3.11
Classifier: Programming Language :: Python :: 3.12
Classifier: Programming Language :: Python :: 3.13
Requires-Dist: awsiotsdk (>=1.5.11,<2.0.0)
Project-URL: Repository, https://github.com/whill-labs/aws-iot-device-client-python
